bheEASyMesh/bhemeshing.py
bheEASyMesh-0.2.3.dist-info/LICENSE
bheEASyMesh-0.2.3.dist-info/METADATA
bheEASyMesh-0.2.3.dist-info/WHEEL
bheEASyMesh-0.2.3.dist-info/top_level.txt
bheEASyMesh-0.2.3.dist-info/RECORD
