Metadata-Version: 2.1
Name: bheEASyMesh
Version: 0.2.3
Summary: Tool for creating FE-meshes for bhe simulations
Home-page: https://github.com/Eqrisi/bheEASyMesh.git
Author: Simon Richter
Author-email: simonr92@gmx.de
Maintainer: Simon Richter
Maintainer-email: simon.richter@htwk-leipzig.de
License: MIT -  see LICENSE.txt
Keywords: Meshing,BHE,GSHP,Finite-Element-Method,OpenGeoSys
Platform: Windows
Platform: Linux
Platform: Mac OS-X
License-File: LICENSE
Requires-Dist: numpy
Requires-Dist: gmsh
Requires-Dist: vtk
Requires-Dist: scipy
